{
  "lessonId": "A1-1-M01-L01",
  "lessonTitle": {
    "de": "Hallo! Ich bin...",
    "fa": "سلام! من هستم..."
  },
  "module": 1,
  "priority": "high",
  "createdAt": "2025-12-26",
  "tasks": [
    {
      "id": "img-01",
      "type": "image",
      "stepId": "s1",
      "stepType": "dialog",
      "description": "Two young adults (Anna and Tom) meeting in a German language classroom. They are shaking hands and smiling. Classroom setting with whiteboard in background showing 'Willkommen!'",
      "context": "Opening dialog where Anna and Tom introduce themselves in German class",
      "specs": {
        "dimensions": "800x600",
        "format": "jpg",
        "style": "friendly, diverse, educational setting"
      },
      "outputPath": "images/A1-1-M01-L01/classroom-introduction.jpg",
      "status": "pending",
      "assignee": null,
      "notes": ""
    },
    {
      "id": "img-02",
      "type": "image",
      "stepId": "s2",
      "stepType": "new-word",
      "description": "Person waving hand in friendly greeting gesture. Casual, approachable pose.",
      "context": "Vocabulary: 'Hallo' (Hello) - casual greeting",
      "specs": {
        "dimensions": "800x600",
        "format": "jpg",
        "style": "friendly, casual, warm colors"
      },
      "outputPath": "images/A1-1-M01-L01/hallo-greeting.jpg",
      "status": "pending",
      "assignee": null,
      "notes": ""
    },
    {
      "id": "img-03",
      "type": "image",
      "stepId": "s3",
      "stepType": "new-word",
      "description": "Two business professionals (man and woman) shaking hands in an office lobby. Formal attire, professional setting.",
      "context": "Vocabulary: 'Guten Tag' (Good day) - formal greeting",
      "specs": {
        "dimensions": "800x600",
        "format": "jpg",
        "style": "professional, formal, business setting"
      },
      "outputPath": "images/A1-1-M01-L01/guten-tag-formal.jpg",
      "status": "pending",
      "assignee": null,
      "notes": ""
    },
    {
      "id": "img-04",
      "type": "image",
      "stepId": "s4",
      "stepType": "new-word",
      "description": "Person stretching/yawning in morning sunlight by a window, or having morning coffee. Sunrise visible through window.",
      "context": "Vocabulary: 'Guten Morgen' (Good morning)",
      "specs": {
        "dimensions": "800x600",
        "format": "jpg",
        "style": "warm, morning light, peaceful"
      },
      "outputPath": "images/A1-1-M01-L01/guten-morgen.jpg",
      "status": "pending",
      "assignee": null,
      "notes": ""
    },
    {
      "id": "img-05",
      "type": "image",
      "stepId": "s5",
      "stepType": "new-word",
      "description": "Person waving goodbye at a train station or office door. Professional context, slightly formal.",
      "context": "Vocabulary: 'Auf Wiedersehen' (Goodbye - formal)",
      "specs": {
        "dimensions": "800x600",
        "format": "jpg",
        "style": "professional, slightly formal"
      },
      "outputPath": "images/A1-1-M01-L01/auf-wiedersehen.jpg",
      "status": "pending",
      "assignee": null,
      "notes": ""
    },
    {
      "id": "img-06",
      "type": "image",
      "stepId": "s6",
      "stepType": "new-word",
      "description": "Two friends (young adults) waving goodbye casually at a cafe or park. Relaxed, informal setting.",
      "context": "Vocabulary: 'Tschüs' (Bye - informal)",
      "specs": {
        "dimensions": "800x600",
        "format": "jpg",
        "style": "casual, friendly, outdoor or cafe"
      },
      "outputPath": "images/A1-1-M01-L01/tschues-casual.jpg",
      "status": "pending",
      "assignee": null,
      "notes": ""
    },
    {
      "id": "vid-01",
      "type": "video",
      "stepId": "s14",
      "stepType": "dialog",
      "description": "Two business professionals (Mr. Schmidt and Mr. Ahmadi) meeting for the first time. They shake hands, exchange formal greetings: 'Guten Tag! Mein Name ist Schmidt. Wie heißen Sie?' - 'Guten Tag, Herr Schmidt. Ich heiße Ahmadi.' - 'Freut mich!' - 'Freut mich auch!'",
      "context": "Formal introduction dialog demonstrating Sie-form and professional greeting",
      "specs": {
        "duration": "15-20 seconds",
        "format": "mp4",
        "resolution": "1080p",
        "audio": "Clear German pronunciation, formal tone"
      },
      "outputPath": "videos/A1-1-M01-L01/formal-introduction.mp4",
      "status": "pending",
      "assignee": null,
      "notes": "Actors should speak slowly and clearly. Include pauses between exchanges."
    }
  ],
  "summary": {
    "totalTasks": 7,
    "images": 6,
    "videos": 1,
    "priority": "Focus on images first, video can come later"
  }
}
