{
  "lessonId": "A2-1-M07-L01",
  "lessonTitle": {
    "de": "Urlaubserlebnisse",
    "fa": "تجربه‌های سفر"
  },
  "module": 7,
  "priority": "high",
  "createdAt": "2025-12-27",
  "tasks": [
    {
      "id": "img-01",
      "type": "image",
      "stepId": "s1",
      "stepType": "dialog",
      "description": "Two friends (Maria and Peter) chatting in an office break room or cafe. Peter has just returned from vacation and is showing vacation photos on his phone to Maria. Both are smiling and engaged in conversation.",
      "context": "Dialog: 'Nach dem Urlaub' - Maria asking Peter about his vacation in Italy",
      "specs": {
        "dimensions": "800x600",
        "format": "jpg",
        "style": "casual, friendly, warm atmosphere"
      },
      "outputPath": "images/A2-1-M07-L01/vacation-conversation.jpg",
      "status": "pending",
      "assignee": null,
      "notes": "",
      "category": "travel"
    },
    {
      "id": "img-02",
      "type": "image",
      "stepId": "s1",
      "stepType": "dialog",
      "description": "Beautiful Italian scenic view - Colosseum in Rome or Venice canals with gondolas. Iconic Italian landmark during summer vacation time.",
      "context": "Dialog context: Peter says 'Ich habe Italien besucht. Wir haben viel gesehen.'",
      "specs": {
        "dimensions": "800x600",
        "format": "jpg",
        "style": "scenic, tourist destination, bright sunny day"
      },
      "outputPath": "images/A2-1-M07-L01/italy-vacation.jpg",
      "status": "pending",
      "assignee": null,
      "notes": "",
      "category": "travel"
    },
    {
      "id": "img-03",
      "type": "image",
      "stepId": "s3",
      "stepType": "new-word",
      "description": "Tourist visiting an art museum or historical museum. Person viewing paintings or sculptures in a gallery. Classical museum interior with artwork on walls.",
      "context": "Vocabulary: 'besuchen' (to visit) - museum visit context",
      "specs": {
        "dimensions": "800x600",
        "format": "jpg",
        "style": "cultural, museum interior, educational"
      },
      "outputPath": "images/A2-1-M07-L01/museum-visit.jpg",
      "status": "pending",
      "assignee": null,
      "notes": "",
      "category": "places"
    },
    {
      "id": "img-04",
      "type": "image",
      "stepId": "s4",
      "stepType": "new-word",
      "description": "Tourist taking photos with a camera or smartphone at a famous landmark. Person framing a shot of scenic view or architectural monument.",
      "context": "Vocabulary: 'fotografieren' (to photograph/take photos)",
      "specs": {
        "dimensions": "800x600",
        "format": "jpg",
        "style": "tourist activity, outdoor, engaging"
      },
      "outputPath": "images/A2-1-M07-L01/taking-photos.jpg",
      "status": "pending",
      "assignee": null,
      "notes": "",
      "category": "travel"
    },
    {
      "id": "img-05",
      "type": "image",
      "stepId": "s8a",
      "stepType": "new-word",
      "description": "Family or couple with luggage at a travel destination - airport arrival area or hotel entrance. Happy travelers beginning their journey. Travel bags, excitement visible.",
      "context": "Vocabulary: 'die Reise' (the trip/journey)",
      "specs": {
        "dimensions": "800x600",
        "format": "jpg",
        "style": "travel, excitement, adventure beginning"
      },
      "outputPath": "images/A2-1-M07-L01/travel-journey.jpg",
      "status": "pending",
      "assignee": null,
      "notes": "",
      "category": "travel"
    },
    {
      "id": "img-06",
      "type": "image",
      "stepId": "s8b",
      "stepType": "new-word",
      "description": "Beautiful beach scene with ocean waves, sandy beach, and blue sky. People swimming or sunbathing. Classic seaside vacation destination.",
      "context": "Vocabulary: 'ans Meer fahren' (to go to the sea/beach)",
      "specs": {
        "dimensions": "800x600",
        "format": "jpg",
        "style": "summer vacation, beach, relaxing, sunny"
      },
      "outputPath": "images/A2-1-M07-L01/beach-vacation.jpg",
      "status": "pending",
      "assignee": null,
      "notes": "",
      "category": "travel"
    },
    {
      "id": "img-07",
      "type": "image",
      "stepId": "s9",
      "stepType": "grammar-tip",
      "description": "Split image or collage showing popular German vacation destinations: Mediterranean beach (Spain/Italy), Alpine mountains (Austria), and German coastal area (Ostsee). Vacation planning concept with calendar showing summer months.",
      "context": "Cultural note: German vacation culture - popular destinations include Italy, Spain, Austria",
      "specs": {
        "dimensions": "800x600",
        "format": "jpg",
        "style": "collage or split-screen, vacation destinations, informative"
      },
      "outputPath": "images/A2-1-M07-L01/german-vacation-culture.jpg",
      "status": "pending",
      "assignee": null,
      "notes": "",
      "category": "travel"
    },
    {
      "id": "vid-01",
      "type": "video",
      "stepId": "s1",
      "stepType": "dialog",
      "description": "Maria and Peter having a conversation after Peter's return from Italy. Scene 1: Office setting. Maria: 'Hallo Peter! Wie war dein Urlaub?' Peter: 'Super! Ich habe Italien besucht. Wir haben viel gesehen.' Maria: 'Was habt ihr gemacht?' Peter: 'Wir haben Museen besucht und viel fotografiert. Das Essen war fantastisch!' Both actors show enthusiasm, Peter can gesture showing vacation photos on phone.",
      "context": "Main dialog demonstrating Perfekt tense with haben and vacation vocabulary",
      "specs": {
        "duration": "20-25 seconds",
        "format": "mp4",
        "resolution": "1080p",
        "audio": "Clear German pronunciation, conversational pace, friendly tone"
      },
      "outputPath": "videos/A2-1-M07-L01/vacation-dialog.mp4",
      "status": "pending",
      "assignee": null,
      "notes": "Actors should be enthusiastic and natural. Peter can show phone photos. Include pauses between exchanges.",
      "category": "travel"
    }
  ],
  "summary": {
    "totalTasks": 8,
    "images": 7,
    "videos": 1,
    "priority": "Focus on images first, video can come later",
    "categories": {
      "travel": 6,
      "places": 1
    },
    "keyVocabulary": [
      "der Urlaub (vacation)",
      "besuchen (to visit)",
      "fotografieren (to photograph)",
      "die Reise (trip/journey)",
      "ans Meer fahren (to go to the beach)"
    ],
    "grammarFocus": "Perfekt tense with haben"
  }
}
