{
  "lessonId": "A1-M03-L02",
  "lessonTitle": {
    "de": "kein/keine",
    "fa": "هیچ / ندارم"
  },
  "sourceHash": "b22b4cdc",
  "generatedAt": "2026-01-06T23:25:16.748Z",
  "updatedAt": "2026-01-06T23:25:16.748Z",
  "tasks": [
    {
      "id": "img-s11",
      "type": "image",
      "stepId": "s11",
      "stepType": "dialog",
      "priority": "high",
      "sourceContent": {
        "title": "مکالمه: ندارم!",
        "speakers": [
          "Eli",
          "Tom"
        ],
        "firstLine": "Gehen wir ins Kino?",
        "lineCount": 6
      },
      "sourceHash": "3c47339d",
      "description": "Eli & Tom - مکالمه: ندارم!",
      "context": "Dialog with 6 lines: \"Gehen wir ins Kino?\"",
      "specs": {
        "format": "jpg",
        "dimensions": "800x600",
        "style": "friendly, modern German setting",
        "subjects": "Eli, Tom"
      },
      "category": "scenes",
      "outputPath": "images/shared/scenes/a1-m03-l02-s11-eli-tom.jpg",
      "status": "pending",
      "completedAt": null,
      "notes": ""
    }
  ]
}